nadej
