Metadata-Version: 1.1
Name: nadej
Version: 0.0.12
Summary: Document generator
Home-page: https://github.com/fanff/nadej.git
Author: fanf
Author-email: fanf@googlegroups.com
License: MIT
Keywords: docs
Platform: UNKNOWN
Classifier: Development Status :: 3 - Alpha
Classifier: Intended Audience :: Developers
Classifier: Topic :: Software Development :: Build Tools
Classifier: License :: OSI Approved :: MIT License
Classifier: Programming Language :: Python :: 2
Classifier: Programming Language :: Python :: 2.6
Classifier: Programming Language :: Python :: 2.7
